objtools/__init__.py
objtools/collections.py
objtools/registry.py
objtools-0.1.1.dist-info/LICENSE
objtools-0.1.1.dist-info/METADATA
objtools-0.1.1.dist-info/WHEEL
objtools-0.1.1.dist-info/top_level.txt
objtools-0.1.1.dist-info/RECORD
