Metadata-Version: 2.1
Name: objtools
Version: 0.1.1
Summary: Miscellaneous helpers for objects.
Home-page: https://gitlab.com/Lucidiot/objtools
Author: Lucidiot
License: GNU General Public License 3
Project-URL: Source Code, https://gitlab.com/Lucidiot/objtools
Project-URL: Bug Tracker, https://gitlab.com/Lucidiot/objtools/issues
Project-URL: GitHub Mirror, https://github.com/Lucidiot/objtools
Keywords: object tools utils utilities
Platform: UNKNOWN
Classifier: Development Status :: 3 - Alpha
Classifier: License :: OSI Approved :: GNU General Public License v3 (GPLv3)
Classifier: Natural Language :: English
Classifier: Intended Audience :: Developers
Classifier: Programming Language :: Python :: 3
Classifier: Programming Language :: Python :: 3 :: Only
Classifier: Programming Language :: Python :: 3.5
Classifier: Programming Language :: Python :: 3.6
Classifier: Programming Language :: Python :: 3.7
Classifier: Topic :: Software Development :: Libraries
Classifier: Topic :: Utilities
Classifier: Typing :: Typed
Requires-Python: >=3.5
Provides-Extra: dev
Requires-Dist: flake8 (>=3.5) ; extra == 'dev'
Requires-Dist: doc8 (>=0.8.0) ; extra == 'dev'
Requires-Dist: Sphinx (>=1.8.1) ; extra == 'dev'
Requires-Dist: coverage (>=4.5) ; extra == 'dev'
Requires-Dist: codecov (>=2.0) ; extra == 'dev'
Requires-Dist: mypy (>=0.720) ; extra == 'dev'
